kivg/__init__.py
kivg/data_classes.py
kivg/main.py
kivg/mesh_handler.py
kivg/path_utils.py
kivg/svg_parser.py
kivg/svg_renderer.py
kivg/version.py
kivg/animation/animation_shapes.py
kivg/animation/handler.py
kivg/animation/kivy_animation.py
kivg/drawing/manager.py
kivg-1.2.dist-info/licenses/LICENSE
kivg-1.2.dist-info/METADATA
kivg-1.2.dist-info/WHEEL
kivg-1.2.dist-info/top_level.txt
kivg-1.2.dist-info/RECORD
