Metadata-Version: 2.4
Name: Kivg
Version: 1.2
Summary: SVG path drawing and animation support in kivy application
Home-page: https://github.com/shashi278/svg-anim-kivy
Author: Shashi Ranjan
Author-email: shashiranjankv@gmail.com
Keywords: svg svg-animations svg-path svg-images kivy-application kivy python
Classifier: Programming Language :: Python :: 3
Classifier: License :: OSI Approved :: MIT License
Classifier: Operating System :: Android
Classifier: Operating System :: Microsoft :: Windows
Classifier: Operating System :: OS Independent
Requires-Python: >=3.6
License-File: LICENSE
Requires-Dist: kivy>=2.0.0
Requires-Dist: svg.path==4.1
Dynamic: author
Dynamic: author-email
Dynamic: classifier
Dynamic: description
Dynamic: description-content-type
Dynamic: home-page
Dynamic: keywords
Dynamic: license-file
Dynamic: requires-dist
Dynamic: requires-python
Dynamic: summary
